{
  "$schema": "https://stencila.org/Article.schema.json",
  "@context": "https://stencila.org/context.jsonld",
  "type": "Article",
  "content": [
    {
      "type": "ForBlock",
      "code": "3",
      "variable": "int",
      "content": [
        {
          "type": "Paragraph",
          "content": [
            {
              "type": "CodeExpression",
              "code": " int "
            }
          ]
        }
      ],
      "iterations": [
        {
          "type": "Section",
          "content": [
            {
              "type": "Paragraph",
              "content": [
                {
                  "type": "CodeExpression",
                  "code": " int ",
                  "output": 0,
                  "executionCount": 1,
                  "executionRequired": "No",
                  "executionStatus": "Succeeded",
                  "executionEnded": {
                    "type": "Timestamp",
                    "value": 1714644386623,
                    "timeUnit": "Millisecond"
                  },
                  "executionDuration": {
                    "type": "Duration",
                    "value": 0,
                    "timeUnit": "Millisecond"
                  }
                }
              ]
            }
          ],
          "sectionType": "Iteration"
        },
        {
          "type": "Section",
          "content": [
            {
              "type": "Paragraph",
              "content": [
                {
                  "type": "CodeExpression",
                  "code": " int ",
                  "output": 1,
                  "executionCount": 1,
                  "executionRequired": "No",
                  "executionStatus": "Succeeded",
                  "executionEnded": {
                    "type": "Timestamp",
                    "value": 1714644386624,
                    "timeUnit": "Millisecond"
                  },
                  "executionDuration": {
                    "type": "Duration",
                    "value": 0,
                    "timeUnit": "Millisecond"
                  }
                }
              ]
            }
          ],
          "sectionType": "Iteration"
        },
        {
          "type": "Section",
          "content": [
            {
              "type": "Paragraph",
              "content": [
                {
                  "type": "CodeExpression",
                  "code": " int ",
                  "output": 2,
                  "executionCount": 1,
                  "executionRequired": "No",
                  "executionStatus": "Succeeded",
                  "executionEnded": {
                    "type": "Timestamp",
                    "value": 1714644386625,
                    "timeUnit": "Millisecond"
                  },
                  "executionDuration": {
                    "type": "Duration",
                    "value": 0,
                    "timeUnit": "Millisecond"
                  }
                }
              ]
            }
          ],
          "sectionType": "Iteration"
        }
      ],
      "compilationDigest": {
        "type": "CompilationDigest",
        "stateDigest": 10489139260846039361
      },
      "executionDigest": {
        "type": "CompilationDigest",
        "stateDigest": 10489139260846039361
      },
      "executionCount": 1,
      "executionRequired": "No",
      "executionStatus": "Succeeded",
      "executionEnded": {
        "type": "Timestamp",
        "value": 1714644386625,
        "timeUnit": "Millisecond"
      },
      "executionDuration": {
        "type": "Duration",
        "value": 5,
        "timeUnit": "Millisecond"
      }
    },
    {
      "type": "ForBlock",
      "code": "\"123\"",
      "variable": "char",
      "content": [
        {
          "type": "Paragraph",
          "content": [
            {
              "type": "CodeExpression",
              "code": " char "
            }
          ]
        }
      ],
      "iterations": [
        {
          "type": "Section",
          "content": [
            {
              "type": "Paragraph",
              "content": [
                {
                  "type": "CodeExpression",
                  "code": " char ",
                  "output": "1",
                  "executionCount": 1,
                  "executionRequired": "No",
                  "executionStatus": "Succeeded",
                  "executionEnded": {
                    "type": "Timestamp",
                    "value": 1714644386626,
                    "timeUnit": "Millisecond"
                  },
                  "executionDuration": {
                    "type": "Duration",
                    "value": 1,
                    "timeUnit": "Millisecond"
                  }
                }
              ]
            }
          ],
          "sectionType": "Iteration"
        },
        {
          "type": "Section",
          "content": [
            {
              "type": "Paragraph",
              "content": [
                {
                  "type": "CodeExpression",
                  "code": " char ",
                  "output": "2",
                  "executionCount": 1,
                  "executionRequired": "No",
                  "executionStatus": "Succeeded",
                  "executionEnded": {
                    "type": "Timestamp",
                    "value": 1714644386626,
                    "timeUnit": "Millisecond"
                  },
                  "executionDuration": {
                    "type": "Duration",
                    "value": 0,
                    "timeUnit": "Millisecond"
                  }
                }
              ]
            }
          ],
          "sectionType": "Iteration"
        },
        {
          "type": "Section",
          "content": [
            {
              "type": "Paragraph",
              "content": [
                {
                  "type": "CodeExpression",
                  "code": " char ",
                  "output": "3",
                  "executionCount": 1,
                  "executionRequired": "No",
                  "executionStatus": "Succeeded",
                  "executionEnded": {
                    "type": "Timestamp",
                    "value": 1714644386626,
                    "timeUnit": "Millisecond"
                  },
                  "executionDuration": {
                    "type": "Duration",
                    "value": 0,
                    "timeUnit": "Millisecond"
                  }
                }
              ]
            }
          ],
          "sectionType": "Iteration"
        }
      ],
      "compilationDigest": {
        "type": "CompilationDigest",
        "stateDigest": 1382367851828009517
      },
      "executionDigest": {
        "type": "CompilationDigest",
        "stateDigest": 1382367851828009517
      },
      "executionCount": 1,
      "executionRequired": "No",
      "executionStatus": "Succeeded",
      "executionEnded": {
        "type": "Timestamp",
        "value": 1714644386626,
        "timeUnit": "Millisecond"
      },
      "executionDuration": {
        "type": "Duration",
        "value": 1,
        "timeUnit": "Millisecond"
      }
    }
  ],
  "executionCount": 1,
  "executionRequired": "No",
  "executionStatus": "Succeeded",
  "executionEnded": {
    "type": "Timestamp",
    "value": 1714644386626,
    "timeUnit": "Millisecond"
  },
  "executionDuration": {
    "type": "Duration",
    "value": 6,
    "timeUnit": "Millisecond"
  }
}